CHANGELOG.txt
LICENSE.txt
MANIFEST.in
README.txt
env.yml
setup.py
.pytest_cache/README.md
datasets/housing/housing.csv
datasets/housing/housing.tgz
datasets/housing/housing_prepared.csv
datasets/housing/testing_prepared.csv
docs/build/html/_sources/code_installation.rst.txt
docs/build/html/_sources/index.rst.txt
docs/build/html/_sources/predict.rst.txt
docs/build/html/_sources/score_pretrained.rst.txt
docs/build/html/_sources/train_model.rst.txt
docs/source/conf.py
gloriahousing/__init__.py
gloriahousing/nonstandardcode.py
gloriahousing/predict.log
gloriahousing/predict.py
gloriahousing/score_pretrained.log
gloriahousing/score_pretrained.py
gloriahousing/train_datasets.py
gloriahousing/train_score_model.log
gloriahousing/train_score_model.py
gloriahousing.egg-info/PKG-INFO
gloriahousing.egg-info/SOURCES.txt
gloriahousing.egg-info/dependency_links.txt
gloriahousing.egg-info/top_level.txt
tests_housing/funtions.py
tests_housing/test_dtype_pytest.py
tests_housing/test_dtype_unittest.py
tests_housing/test_housing_pytest.py
tests_housing/test_housing_unittest.py
tests_housing/var_dtype.py