Metadata-Version: 1.1
Name: gloriahousing
Version: 0.0.1
Summary: Predicts Median housing value
Home-page: UNKNOWN
Author: Gloria Joseph
Author-email: gloria.joseph@tigeranalytics.com
License: MIT
Keywords: median
Platform: UNKNOWN
Classifier: Development Status :: 5 - Production/Stable
Classifier: Intended Audience :: Education
Classifier: Operating System :: Microsoft :: Windows :: Windows 10
Classifier: License :: OSI Approved :: MIT License
Classifier: Programming Language :: Python :: 3
